utils/__init__.py
utils/audio_converter.py
hr_edge_recruit_mcp_server-0.1.0.dist-info/METADATA
hr_edge_recruit_mcp_server-0.1.0.dist-info/WHEEL
hr_edge_recruit_mcp_server-0.1.0.dist-info/entry_points.txt
hr_edge_recruit_mcp_server-0.1.0.dist-info/top_level.txt
hr_edge_recruit_mcp_server-0.1.0.dist-info/RECORD
