Metadata-Version: 2.4
Name: hr-edge-recruit-mcp-server
Version: 0.1.0
Summary: A custom MCP server using FastAPI, AWS, Firebase, and LangChain for real-time audio analysis.
Home-page: https://github.com/yourusername/mcp-server
Author: LLM Lords
Author-email: prathameshb@incubxperts.com
Classifier: Programming Language :: Python :: 3.11
Classifier: Framework :: FastAPI
Classifier: License :: OSI Approved :: MIT License
Classifier: Operating System :: OS Independent
Requires-Python: >=3.9
Requires-Dist: fastapi==0.104.1
Requires-Dist: uvicorn==0.24.0
Requires-Dist: pydantic==2.5.0
Requires-Dist: python-multipart==0.0.6
Requires-Dist: boto3>=1.39.7
Requires-Dist: langchain
Requires-Dist: langchain-community
Requires-Dist: langchain-aws
Requires-Dist: pinecone-client==2.2.4
Requires-Dist: openai==1.3.7
Requires-Dist: python-dotenv==1.0.0
Requires-Dist: requests==2.31.0
Requires-Dist: aiofiles==23.2.1
Requires-Dist: python-jose[cryptography]==3.3.0
Requires-Dist: passlib[bcrypt]==1.7.4
Requires-Dist: cryptography==41.0.7
Requires-Dist: pytest==7.4.3
Requires-Dist: pytest-asyncio==0.21.1
Requires-Dist: httpx==0.25.2
Requires-Dist: firebase-admin==6.2.0
Requires-Dist: google-cloud-firestore==2.13.1
Requires-Dist: websockets==12.0
Requires-Dist: numpy==1.24.3
Requires-Dist: asyncio-mqtt==0.16.1
Requires-Dist: aiohttp==3.9.1
Requires-Dist: PyPDF2==3.0.1
Requires-Dist: pdfplumber==0.10.3
Dynamic: author
Dynamic: author-email
Dynamic: classifier
Dynamic: description
Dynamic: description-content-type
Dynamic: home-page
Dynamic: requires-dist
Dynamic: requires-python
Dynamic: summary
